wsminer/__init__.py
wsminer/binvox.py
wsminer/palette.py
wsminer/server/__main__.py
wsminer-0.1.dist-info/LICENSE
wsminer-0.1.dist-info/METADATA
wsminer-0.1.dist-info/WHEEL
wsminer-0.1.dist-info/top_level.txt
wsminer-0.1.dist-info/RECORD
