Metadata-Version: 2.1
Name: wsminer
Version: 0.1
Summary: Utilities for automating Minecraft building via the Minecraft websocket API
Author-email: Matthew Feinberg <matthew.feinberg@gmail.com>
Project-URL: Homepage, https://github.com/ketbra/wsminert
Project-URL: Bug Tracker, https://github.com/ketbra/wsminer/issues
Classifier: Programming Language :: Python :: 3
Classifier: License :: OSI Approved :: MIT License
Classifier: Operating System :: OS Independent
Classifier: Intended Audience :: Education
Classifier: Topic :: Games/Entertainment
Requires-Python: >=3.7
License-File: LICENSE
Requires-Dist: numpy (>=1.24.2)
Requires-Dist: Pillow (>=9.5.0)
Requires-Dist: scikit-learn (>=1.2.2)
Requires-Dist: websockets (>=10.4)
